{
    "object_id": "16",
    "rmse_position": "0.0103066939844302",
    "rmse_velocity": "6.59357019979055e-05",
    "minimum_deviations": {
        "position": {
            "X_diff": "3.90962510010695e-06",
            "Y_diff": "7.58929193889202e-06",
            "Z_diff": "1.27782200551319e-06"
        },
        "velocity": {
            "Vx_diff": "2.63343054999251e-08",
            "Vy_diff": "2.93560667996573e-08",
            "Vz_diff": "1.35052899961387e-10"
        }
    },
    "maximum_deviations": {
        "position": {
            "X_diff": "0.0450620422384231",
            "Y_diff": "0.06608550059164",
            "Z_diff": "0.0022828697551828"
        },
        "velocity": {
            "Vx_diff": "0.0004621379388133",
            "Vy_diff": "0.000389666133237",
            "Vz_diff": "2.24622948720999e-05"
        }
    },
    "max_absolute_differences": {
        "X_diff": "0.0450620422384231",
        "Y_diff": "0.06608550059164",
        "Z_diff": "0.0022828697551828",
        "Vx_diff": "0.0004621379388133",
        "Vy_diff": "0.000389666133237",
        "Vz_diff": "2.24622948720999e-05"
    }
}